MANIFEST.in
README.md
requirements.txt
setup.cfg
setup.py
ga_segment_pusher/__init__.py
ga_segment_pusher.egg-info/PKG-INFO
ga_segment_pusher.egg-info/SOURCES.txt
ga_segment_pusher.egg-info/dependency_links.txt
ga_segment_pusher.egg-info/requires.txt
ga_segment_pusher.egg-info/top_level.txt