Metadata-Version: 1.1
Name: ga-segment-pusher
Version: 0.0.2
Summary: A python package to push user segmentation mapped to google analytics ID to google analytics.
Home-page: https://github.com/rok/ga_segment_pusher
Author: Rok Mihevc
Author-email: rok.mihevc@gmail.com
License: BSD
Download-URL: https://github.com/rok/ga_segment_pusher/tarball/0.0.2
Platform: UNKNOWN
Classifier: Development Status :: 3 - Alpha
Classifier: Intended Audience :: Developers
Classifier: Programming Language :: Python :: 3
